CHANGES.txt
README.txt
bootstrap.py
buildout.cfg
setup.py
test-plone-3.x.cfg
test-plone-4.x.cfg
docs/LICENSE.GPL
docs/LICENSE.txt
pipbox/__init__.py
pipbox.portlet.popform.egg-info/PKG-INFO
pipbox.portlet.popform.egg-info/SOURCES.txt
pipbox.portlet.popform.egg-info/dependency_links.txt
pipbox.portlet.popform.egg-info/entry_points.txt
pipbox.portlet.popform.egg-info/namespace_packages.txt
pipbox.portlet.popform.egg-info/not-zip-safe
pipbox.portlet.popform.egg-info/requires.txt
pipbox.portlet.popform.egg-info/top_level.txt
pipbox/portlet/__init__.py
pipbox/portlet/popform/__init__.py
pipbox/portlet/popform/configure.zcml
pipbox/portlet/popform/popupform.pt
pipbox/portlet/popform/popupform.py
pipbox/portlet/popform/version.txt
pipbox/portlet/popform/profiles/default/metadata.xml
pipbox/portlet/popform/profiles/default/portlets.xml
pipbox/portlet/popform/tests/__init__.py
pipbox/portlet/popform/tests/base.py
pipbox/portlet/popform/tests/test_portlet.py