Metadata-Version: 1.0
Name: pipbox.portlet.popform
Version: 1.1
Summary: Timed PloneFormGen form popup configured via portlet
Home-page: http://plone.org/products/pipbox.portlet.popform
Author: Steve McMahon
Author-email: plone-developers@lists.sourceforge.net
License: GPL
Keywords: pipbox
Platform: UNKNOWN
Classifier: Framework :: Plone
Classifier: Programming Language :: Python
